{
    "OTHER": [
        {
            "title": "Defense Personal Property System (DPS)",
            "link": "https://dps.move.mil/cust/standard/user/home.xhtml"
        },
        {
            "title": "DEERS",
            "link": "https://milconnect.dmdc.osd.mil/milconnect/"
        },
        {
            "title": "ID Card Office Online (Appointments, Update GAL)",
            "link": "https://idco.dmdc.osd.mil/idco/"
        },
        {
            "title": "myFitness (myFSS)",
            "link": "https://myfss.us.af.mil/USAFCommunity/s/usaf-fitness-management"
        },
        {
            "title": "My Force Support Squadron / myFSS",
            "link": "https://myfss.us.af.mil/"
        },
        {
            "title": "Webmail / OWA / E-mail / email",
            "link": "https://webmail.apps.mil/"
        },
        {
            "title": "USAF Publications and Forms (epubs)",
            "link": "https://www.e-publishing.af.mil/Product-Index/"
        },
        {
            "title": "Talent Marketplace (MyVector)",
            "link": "https://myvector.us.af.mil/myvector"
        },
        {
            "title": "GAL Information Update (Update Outlook GAL Profile)",
            "link": "https://esd.us.af.mil"
        },
        {
            "title": "Air Force Portal",
            "link": "https://my.af.mil"
        }
    ]
}
